voxelmorph/__init__.py
voxelmorph/generators.py
voxelmorph/py/__init__.py
voxelmorph/py/utils.py
voxelmorph/tf/__init__.py
voxelmorph/tf/layers.py
voxelmorph/tf/losses.py
voxelmorph/tf/networks.py
voxelmorph/tf/utils/__init__.py
voxelmorph/tf/utils/utils.py
voxelmorph/torch/__init__.py
voxelmorph/torch/layers.py
voxelmorph/torch/losses.py
voxelmorph/torch/modelio.py
voxelmorph/torch/networks.py
voxelmorph/torch/utils.py
voxelmorph-0.2.dist-info/LICENSE.md
voxelmorph-0.2.dist-info/METADATA
voxelmorph-0.2.dist-info/WHEEL
voxelmorph-0.2.dist-info/top_level.txt
voxelmorph-0.2.dist-info/RECORD
